picsl_cmrep.cpython-312-x86_64-linux-gnu.so
picsl_cmrep.libs/libvtkIOPLY-9-0398eb92.3.so
picsl_cmrep.libs/libvtkImagingCore-9-8e22e107.3.so
picsl_cmrep.libs/libvtkFiltersHybrid-9-88f16642.3.so
picsl_cmrep.libs/libvtkpng-9-44166a15.3.so
picsl_cmrep.libs/libvtkRenderingCore-9-7ec7c574.3.so
picsl_cmrep.libs/libvtkCommonSystem-9-eb90f803.3.so
picsl_cmrep.libs/libvtkjpeg-9-3fc7c0e7.3.so
picsl_cmrep.libs/libvtkImagingSources-9-641fba85.3.so
picsl_cmrep.libs/libvtklz4-9-a47b188b.3.so
picsl_cmrep.libs/libvtkFiltersGeneral-9-d56e54f0.3.so
picsl_cmrep.libs/libvtkFiltersGeometry-9-cb7e517d.3.so
picsl_cmrep.libs/libvtkCommonMisc-9-8188684e.3.so
picsl_cmrep.libs/libvtkIOCore-9-05cd2667.3.so
picsl_cmrep.libs/libvtkCommonCore-9-e86a2665.3.so
picsl_cmrep.libs/libvtkFiltersSources-9-c18249c1.3.so
picsl_cmrep.libs/libvtktiff-9-f7af9ed1.3.so
picsl_cmrep.libs/libvtkmetaio-9-47f5ab61.3.so
picsl_cmrep.libs/libvtkloguru-9-61760189.3.so
picsl_cmrep.libs/libvtkfmt-9-2ed071c0.3.so
picsl_cmrep.libs/libvtkCommonTransforms-9-ca645d84.3.so
picsl_cmrep.libs/libvtkDICOMParser-9-8c4bab04.3.so
picsl_cmrep.libs/libvtklzma-9-face83db.3.so
picsl_cmrep.libs/libvtkIOLegacy-9-16e33ade.3.so
picsl_cmrep.libs/libvtkCommonMath-9-da928a53.3.so
picsl_cmrep.libs/libvtkCommonColor-9-3594d6b9.3.so
picsl_cmrep.libs/libvtkpugixml-9-e6982719.3.so
picsl_cmrep.libs/libvtkCommonDataModel-9-9180d4f8.3.so
picsl_cmrep.libs/libvtkIOImage-9-f4d2c8c4.3.so
picsl_cmrep.libs/libvtkCommonComputationalGeometry-9-35ec0f5d.3.so
picsl_cmrep.libs/libvtkFiltersModeling-9-ef851265.3.so
picsl_cmrep.libs/libvtkCommonExecutionModel-9-71fff6e5.3.so
picsl_cmrep.libs/libvtkdoubleconversion-9-7b27019f.3.so
picsl_cmrep.libs/libvtkzlib-9-4a9dc01d.3.so
picsl_cmrep.libs/libvtkFiltersVerdict-9-8764b34d.3.so
picsl_cmrep.libs/libvtkkissfft-9-9bdd9699.3.so
picsl_cmrep.libs/libvtksys-9-95bed46d.3.so
picsl_cmrep.libs/libvtkverdict-9-8fdbf696.3.so
picsl_cmrep.libs/libvtkIOGeometry-9-0ed454d9.3.so
picsl_cmrep-1.0.4.0.dist-info/METADATA
picsl_cmrep-1.0.4.0.dist-info/WHEEL
picsl_cmrep-1.0.4.0.dist-info/RECORD
picsl_cmrep-1.0.4.0.dist-info/licenses/LICENSE
