Metadata-Version: 2.2
Name: picsl_cmrep
Version: 1.0.4.0
Summary: CMRep: Continuous Medial Representation and Related Tools
Author-Email: "Paul A. Yushkevich" <pyushkevich@gmail.com>
Maintainer-Email: "Paul A. Yushkevich" <pyushkevich@gmail.com>
License:                     GNU GENERAL PUBLIC LICENSE
Classifier: Development Status :: 4 - Beta
Classifier: License :: OSI Approved :: BSD License
Classifier: Programming Language :: Python :: 3 :: Only
Classifier: Programming Language :: Python :: 3.8
Classifier: Programming Language :: Python :: 3.9
Classifier: Programming Language :: Python :: 3.10
Classifier: Programming Language :: Python :: 3.11
Classifier: Programming Language :: Python :: 3.12
Classifier: Topic :: Scientific/Engineering :: Physics
Project-URL: Homepage, https://github.com/pyushkevich/cmrep
Project-URL: Documentation, https://cmrep.readthedocs.io/en/latest/
Requires-Python: >=3.8
Requires-Dist: typing_extensions
